iotdb/IoTDBContainer.py
iotdb/Session.py
iotdb/__init__.py
iotdb/thrift/__init__.py
iotdb/thrift/cluster/RaftService.py
iotdb/thrift/cluster/TSDataService.py
iotdb/thrift/cluster/TSMetaService.py
iotdb/thrift/cluster/__init__.py
iotdb/thrift/cluster/constants.py
iotdb/thrift/cluster/ttypes.py
iotdb/thrift/rpc/TSIService.py
iotdb/thrift/rpc/__init__.py
iotdb/thrift/rpc/constants.py
iotdb/thrift/rpc/ttypes.py
iotdb/thrift/sync/SyncService.py
iotdb/thrift/sync/__init__.py
iotdb/thrift/sync/constants.py
iotdb/thrift/sync/ttypes.py
iotdb/utils/Field.py
iotdb/utils/IoTDBConstants.py
iotdb/utils/IoTDBRpcDataSet.py
iotdb/utils/RowRecord.py
iotdb/utils/SessionDataSet.py
iotdb/utils/Tablet.py
iotdb/utils/__init__.py
tests/__init__.py
tests/test_dataframe.py
apache_iotdb_nightly-0.11.2.20210408.dist-info/LICENSE
apache_iotdb_nightly-0.11.2.20210408.dist-info/METADATA
apache_iotdb_nightly-0.11.2.20210408.dist-info/WHEEL
apache_iotdb_nightly-0.11.2.20210408.dist-info/top_level.txt
apache_iotdb_nightly-0.11.2.20210408.dist-info/RECORD
