Metadata-Version: 2.1
Name: apache-iotdb-nightly
Version: 0.11.2.20210408
Summary: Apache IoTDB client API
Home-page: https://github.com/apache/iotdb
Author: Apache Software Foundation
Author-email: dev@iotdb.apache.org
License: Apache License, Version 2.0
Platform: UNKNOWN
Classifier: Programming Language :: Python :: 3
Classifier: License :: OSI Approved :: Apache Software License
Classifier: Operating System :: OS Independent
Classifier: Topic :: Software Development :: Libraries
Classifier: Topic :: Software Development :: Libraries :: Python Modules
Requires-Python: >=3.7
Requires-Dist: thrift (>=0.13.0)
Requires-Dist: pandas (<1.99.99,>=1.0.0)
Requires-Dist: testcontainers (>=2.0.0)
